xenosite/__init__.py
xenosite/__main__.py
xenosite/_version.py
xenosite-0a1.dist-info/entry_points.txt
xenosite-0a1.dist-info/WHEEL
xenosite-0a1.dist-info/METADATA
xenosite-0a1.dist-info/RECORD
